<!--
    External XML documentation for Core.Avatar classes
    u250825
-->

<TngnOpto>

    <Class name="AvtrEnvironment">

        <!--
            <include file='AppData/XmlDoc/Core.Avatar.xml' path='TngnOpto/Class[@name="AvtrEnvironment"]/ClassDescription/*'/>
        -->
        <ClassDescription>
            <para>
                The Avatar Environment represents the <see cref="AvtrSys"><i>System</i></see> and Avatar <see cref="AvtrSysCode"><i>System <b>Code</b></i></see>.<br/>
                <br/>
                While both contain the word <i>System</i>, they are not the same! It is important to understand the difference between the two.<br/>
                <include file='AppData/XmlDoc/ProjectInfo.xml' path='ProjectInfo/Class[@name="Project"]/Callback/*'/>
            </para>
        </ClassDescription>

        <!--
            <include file='../../outpost31/src/AppData/XmlDoc/Core.Avatar.AvtrEnvironment.xml' path='TngnOpto/Class[@name="Core.Avatar.AvtrEnvironment"]/AvtrSys/*'/>
            <include file='AppData/XmlDoc/Common.xml' path='TngnOpto/Class[@name="Common"]/AvtrSys/*'/>
        -->
        <AvtrSys>
            <para>
                The Avatar <see cref="Outpost31.Core.Avatar.AvtrSystem.AvtrSys">
                    <i>System</i>
                </see> represents the <br/>
                Avatar <i>environment</i> that the Tingen Web Service interfaces with.<br/>
                <br/>
                Common Avatar Systems include <c>UAT</c> and <c>LIVE</c>.
                <br/>
                The Avatar <i>System</i> is different than the Avatar <i>System Code</i>.<br/>
            </para>
        </AvtrSys>



        <!--
            <include file='AppData/XmlDoc/%ClassName%.xml' path='TngnOpto/Class[@name="%ClassName%"]/%MethodName%/*'/>
        -->
        <MethodName>
            <para>
                The name of the Executing Assembly is a required component of all log files, as it is used to identify
                the class that is creating the log.<br/>
                <br/>
                This is defined at the start of each class, so it can be used at any time that a log needs to be created.
            </para>
        </MethodName>

    </Class>

</TngnOpto>