<Manual>

    <Topic name="AvtrSys">


        <Information> 
            <para>

       
            </para>
        </Information>

        <Modify> <!-- <include file='AppData/XmlDoc/Manual.xml' path='Manual/Topic[@name="AvtrSys"]/Modify/*'/> -->
            <para>

                <note title="Modifying AvtrSys">
                    To modify the AvtrSys setting:
                    <list type="number">
                        <item>Open the <c>Web.Config</c> file located in the root directory of the Tingen Web Service.</item>
                        <item>Locate the <c>AvtrSys</c> setting within the <c>applicationSettings</c> section.</item>
                        <item>Change the value of the <c>AvtrSys</c> setting to the desired value.</item>
                        <item>Save the changes to the <c>Web.Config</c> file.</item>
                    </list>
                    For example, to set the Avatar System to `LIVE`, modify the setting as follows:
                    <code>
                &lt;setting name="AvtrSys" serializeAs="String"&gt;
                    &lt;value&gt;LIVE&lt;/value&gt;
                &lt;/setting&gt;
                    </code>
                    <br/>
        
                </note>
            </para>
        </Modify>

    </Topic>

</Manual>